winiscraper/__init__.py
winiscraper-2.0.dist-info/LICENSE
winiscraper-2.0.dist-info/METADATA
winiscraper-2.0.dist-info/WHEEL
winiscraper-2.0.dist-info/top_level.txt
winiscraper-2.0.dist-info/RECORD
