Metadata-Version: 2.1
Name: winiscraper
Version: 2.0
Summary: Un scraper rapide basé sur httpx et selectolax
Author: soldat205
License: MIT
Classifier: Programming Language :: Python :: 3
Classifier: License :: OSI Approved :: MIT License
Classifier: Operating System :: OS Independent
Requires-Python: >=3.7
License-File: LICENSE
Requires-Dist: httpx
Requires-Dist: selectolax
